{
  "topic": "TOEIC Day 7 - Technology at Work",
  "words": [
    {"word": "analytics", "partOfSpeech": "n.", "ipa": "/ˌænəˈlɪtɪks/", "meaning": "phân tích dữ liệu"},
    {"word": "application", "partOfSpeech": "n.", "ipa": "/ˌæplɪˈkeɪʃn/", "meaning": "ứng dụng"},
    {"word": "bandwidth", "partOfSpeech": "n.", "ipa": "/ˈbændwɪθ/", "meaning": "băng thông"},
    {"word": "bug", "partOfSpeech": "n.", "ipa": "/bʌɡ/", "meaning": "lỗi phần mềm"},
    {"word": "cloud computing", "partOfSpeech": "n. phr.", "ipa": "/ˌklaʊd kəmˈpjuːtɪŋ/", "meaning": "điện toán đám mây"},
    {"word": "configure", "partOfSpeech": "v.", "ipa": "/kənˈfɪɡə/", "meaning": "cấu hình"},
    {"word": "cybersecurity", "partOfSpeech": "n.", "ipa": "/ˌsaɪbəsɪˈkjʊərəti/", "meaning": "an ninh mạng"},
    {"word": "database", "partOfSpeech": "n.", "ipa": "/ˈdeɪtəbeɪs/", "meaning": "cơ sở dữ liệu"},
    {"word": "encrypt", "partOfSpeech": "v.", "ipa": "/ɪnˈkrɪpt/", "meaning": "mã hóa"},
    {"word": "firewall", "partOfSpeech": "n.", "ipa": "/ˈfaɪəwɔːl/", "meaning": "tường lửa"},
    {"word": "hardware", "partOfSpeech": "n.", "ipa": "/ˈhɑːdweə/", "meaning": "phần cứng"},
    {"word": "interface", "partOfSpeech": "n.", "ipa": "/ˈɪntəfeɪs/", "meaning": "giao diện"},
    {"word": "login credentials", "partOfSpeech": "n. phr.", "ipa": "/ˈlɒɡɪn krɪˈdenʃlz/", "meaning": "thông tin đăng nhập"},
    {"word": "network", "partOfSpeech": "n.", "ipa": "/ˈnetwɜːk/", "meaning": "mạng lưới"},
    {"word": "outage", "partOfSpeech": "n.", "ipa": "/ˈaʊtɪdʒ/", "meaning": "mất điện, gián đoạn"},
    {"word": "password policy", "partOfSpeech": "n. phr.", "ipa": "/ˈpɑːswɜːd ˈpɒləsi/", "meaning": "chính sách mật khẩu"},
    {"word": "reboot", "partOfSpeech": "v.", "ipa": "/ˌriːˈbuːt/", "meaning": "khởi động lại"},
    {"word": "router", "partOfSpeech": "n.", "ipa": "/ˈruːtə/", "meaning": "bộ định tuyến"},
    {"word": "software", "partOfSpeech": "n.", "ipa": "/ˈsɒftweə/", "meaning": "phần mềm"},
    {"word": "storage", "partOfSpeech": "n.", "ipa": "/ˈstɔːrɪdʒ/", "meaning": "lưu trữ"},
    {"word": "troubleshoot", "partOfSpeech": "v.", "ipa": "/ˈtrʌblʃuːt/", "meaning": "khắc phục sự cố"},
    {"word": "update", "partOfSpeech": "n.", "ipa": "/ˈʌpdeɪt/", "meaning": "bản cập nhật"},
    {"word": "upload", "partOfSpeech": "v.", "ipa": "/ˈʌpləʊd/", "meaning": "tải lên"},
    {"word": "version control", "partOfSpeech": "n. phr.", "ipa": "/ˈvɜːʒn kənˈtrəʊl/", "meaning": "quản lý phiên bản"},
    {"word": "wireless", "partOfSpeech": "adj.", "ipa": "/ˈwaɪələs/", "meaning": "không dây"}
  ]
}
